rpa_logger/__init__.py
rpa_logger/_version.py
rpa_logger/logger.py
rpa_logger/task.py
rpa_logger/utils/__init__.py
rpa_logger/utils/args.py
rpa_logger/utils/output.py
rpa_logger/utils/terminal.py
rpa_logger-0.4.1.dist-info/LICENSE
rpa_logger-0.4.1.dist-info/METADATA
rpa_logger-0.4.1.dist-info/WHEEL
rpa_logger-0.4.1.dist-info/top_level.txt
rpa_logger-0.4.1.dist-info/RECORD
