Metadata-Version: 2.1
Name: rpa-logger
Version: 0.4.1
Summary: A simple python package for logging robotic process automation (RPA) progress.
Home-page: https://github.com/kangasta/rpa_logger
Author: Toni Kangas
License: UNKNOWN
Project-URL: Documentation, https://kangasta.github.io/rpa_logger/
Project-URL: Source, https://github.com/kangasta/rpa_logger/
Project-URL: Tracker, https://github.com/kangasta/rpa_logger/issues/
Platform: UNKNOWN
Classifier: Programming Language :: Python :: 3
Classifier: License :: OSI Approved :: MIT License
Classifier: Operating System :: OS Independent
License-File: LICENSE
